goppy/__init__.py
goppy/core.py
goppy/growable.py
goppy/kernel.py
goppy/test/__init__.py
goppy/test/conftest.py
goppy/test/test_core.py
goppy/test/test_growable.py
goppy/test/test_kernel.py
goppy-1.1.2.dist-info/LICENSE
goppy-1.1.2.dist-info/METADATA
goppy-1.1.2.dist-info/WHEEL
goppy-1.1.2.dist-info/RECORD
