Metadata-Version: 2.1
Name: goppy
Version: 1.1.2
Summary: GopPy (Gaussian Online Processes for Python) is a pure Python module providing a Gaussian process implementation which allows 'to efficiently add new data online.
Home-page: https://github.com/jgosmann/goppy
License: MIT
Keywords: Gaussian processes,machine learning,online learning
Author: Jan Gosmann
Author-email: jan@hyper-world.de
Requires-Python: >=3.9
Classifier: Development Status :: 5 - Production/Stable
Classifier: Intended Audience :: Developers
Classifier: Intended Audience :: Information Technology
Classifier: Intended Audience :: Science/Research
Classifier: License :: OSI Approved :: MIT License
Classifier: Programming Language :: Python
Classifier: Programming Language :: Python :: 3
Classifier: Programming Language :: Python :: 3.9
Classifier: Programming Language :: Python :: 3.10
Classifier: Programming Language :: Python :: 3.11
Classifier: Programming Language :: Python :: 3.12
Classifier: Programming Language :: Python :: 3.13
Classifier: Topic :: Scientific/Engineering
Classifier: Topic :: Software Development
Requires-Dist: numpy (>=1.26.0,<3)
Project-URL: Documentation, https://goppy.readthedocs.io/en/latest/
Project-URL: Repository, https://github.com/jgosmann/goppy
